wsaplus/__init__.py
wsaplus/api.py
wsaplus/cli.py
wsaplus/model.py
wsaplus-0.1.2.dist-info/licenses/LICENSE
wsaplus-0.1.2.dist-info/METADATA
wsaplus-0.1.2.dist-info/WHEEL
wsaplus-0.1.2.dist-info/entry_points.txt
wsaplus-0.1.2.dist-info/top_level.txt
wsaplus-0.1.2.dist-info/RECORD
