Metadata-Version: 2.4
Name: wsaplus
Version: 0.1.2
Summary: WSA+: generate solar wind speed maps from synoptic magnetograms
Author: Prateek Mayank, Enrico Camporeale
License: MIT License
Project-URL: Homepage, https://github.com/PrateekMayank/wsaplus_pythonpackage
Project-URL: Source, https://github.com/PrateekMayank/wsaplus_pythonpackage
Project-URL: Issues, https://github.com/PrateekMayank/wsaplus_pythonpackage/issues
Project-URL: Zenodo, https://doi.org/10.5281/zenodo.17309172
Keywords: solar wind,PFSS,sunpy,astropy,pfsspy,WSA,deep learning
Classifier: Programming Language :: Python :: 3
Classifier: License :: OSI Approved :: MIT License
Classifier: Operating System :: OS Independent
Classifier: Intended Audience :: Science/Research
Classifier: Topic :: Scientific/Engineering :: Physics
Requires-Python: >=3.8
License-File: LICENSE
Requires-Dist: numpy>=1.22
Requires-Dist: scipy>=1.10
Requires-Dist: astropy>=5.0
Requires-Dist: sunpy>=5.0
Requires-Dist: pfsspy>=1.2.0
Requires-Dist: streamtracer>=1.1.2
Requires-Dist: scikit-learn>=1.1
Requires-Dist: numba>=0.57
Requires-Dist: joblib>=1.2
Requires-Dist: timm>=0.9
Dynamic: license-file
